quant_experiment/__init__.py
quant_experiment/constants.py
quant_experiment/finproducts.py
quant_experiment/mathformulas.py
quant_experiment/quantexperiment.py
quant_experiment-1.0.4.dist-info/METADATA
quant_experiment-1.0.4.dist-info/RECORD
quant_experiment-1.0.4.dist-info/WHEEL
quant_experiment-1.0.4.dist-info/top_level.txt
test_quant_experiment/__init__.py
test_quant_experiment/test_finproducts.py
